my_test_hive_1_ti_client/__init__.py
my_test_hive_1_ti_client/api_client.py
my_test_hive_1_ti_client/api_response.py
my_test_hive_1_ti_client/configuration.py
my_test_hive_1_ti_client/exceptions.py
my_test_hive_1_ti_client/py.typed
my_test_hive_1_ti_client/rest.py
my_test_hive_1_ti_client/api/__init__.py
my_test_hive_1_ti_client/api/gifs_api.py
my_test_hive_1_ti_client/api/stickers_api.py
my_test_hive_1_ti_client/models/__init__.py
my_test_hive_1_ti_client/models/get_gifs_by_id200_response.py
my_test_hive_1_ti_client/models/gif.py
my_test_hive_1_ti_client/models/gif_images.py
my_test_hive_1_ti_client/models/gif_images_downsized.py
my_test_hive_1_ti_client/models/gif_images_downsized_large.py
my_test_hive_1_ti_client/models/gif_images_downsized_medium.py
my_test_hive_1_ti_client/models/gif_images_downsized_small.py
my_test_hive_1_ti_client/models/gif_images_downsized_still.py
my_test_hive_1_ti_client/models/gif_images_fixed_height.py
my_test_hive_1_ti_client/models/gif_images_fixed_height_downsampled.py
my_test_hive_1_ti_client/models/gif_images_fixed_height_small.py
my_test_hive_1_ti_client/models/gif_images_fixed_height_small_still.py
my_test_hive_1_ti_client/models/gif_images_fixed_height_still.py
my_test_hive_1_ti_client/models/gif_images_fixed_width.py
my_test_hive_1_ti_client/models/gif_images_fixed_width_downsampled.py
my_test_hive_1_ti_client/models/gif_images_fixed_width_small.py
my_test_hive_1_ti_client/models/gif_images_fixed_width_small_still.py
my_test_hive_1_ti_client/models/gif_images_fixed_width_still.py
my_test_hive_1_ti_client/models/gif_images_looping.py
my_test_hive_1_ti_client/models/gif_images_original.py
my_test_hive_1_ti_client/models/gif_images_original_still.py
my_test_hive_1_ti_client/models/gif_images_preview.py
my_test_hive_1_ti_client/models/gif_images_preview_gif.py
my_test_hive_1_ti_client/models/image.py
my_test_hive_1_ti_client/models/meta.py
my_test_hive_1_ti_client/models/pagination.py
my_test_hive_1_ti_client-1.0.0.dist-info/METADATA
my_test_hive_1_ti_client-1.0.0.dist-info/WHEEL
my_test_hive_1_ti_client-1.0.0.dist-info/top_level.txt
my_test_hive_1_ti_client-1.0.0.dist-info/RECORD
